charon/__init__.py
charon/core.py
charon_tle-0.2.0.dist-info/METADATA
charon_tle-0.2.0.dist-info/WHEEL
charon_tle-0.2.0.dist-info/licenses/LICENSE
charon_tle-0.2.0.dist-info/RECORD
